[

  {
    "url": "/gallery/image (3).png",
    "date": "August 2016",
    "location": "https://withagency.com/",
    "direction": "vertical"
  },
  {
    "url": "/gallery/image (4).png",
    "date": "April 2017",
    "location": "https://scapeid.com/",
    "direction": "vertical"
  },
  {
    "url": "/gallery/image (1).png",
    "date": "June 2019",
    "location": "https://www.futuragp.com/",
    "direction": "vertical"
  },
  {
    "url": "/gallery/image (6).png",
    "date": "Mar 2020",
    "location": "https://f11fa0-3.myshopify.com/",
    "direction": "vertical"
  },
  {
    "url": "/gallery/image (9).png",
    "date": "November 2020",
    "location": "https://thalimconstruction.co.uk/",
    "direction": "vertical"
  },
  {
    "url": "/gallery/Screenshot_3.png",
    "date": "September 2021",
    "location": "https://credpal.netlify.app/",
    "direction": "vertical"
  },
  {
    "url": "/gallery/Screenshot_9.png",
    "date": "Mar 2023",
    "location": "http://fitsat6.websolutions.pp.ua/",
    "direction": "vertical"
  },
  {
    "url": "/gallery/Screenshot_10.png",
    "date": "Mar 2024",
    "location": "https://livefeather.com/",
    "direction": "vertical"
  } 

]